setup.py
lifecycle/__init__.py
lifecycle/lifecycle.py
lifecycle/test_lifecycle.py
lifecycle.egg-info/PKG-INFO
lifecycle.egg-info/SOURCES.txt
lifecycle.egg-info/dependency_links.txt
lifecycle.egg-info/not-zip-safe
lifecycle.egg-info/requires.txt
lifecycle.egg-info/top_level.txt