Metadata-Version: 1.0
Name: lifecycle
Version: 0.5
Summary: Easily identify and track users with minimal code.
Home-page: https://github.com/TeamLifecycle/lifecycle-python
Author: Jake Mooney
Author-email: jrmooney@gmail.com
License: MIT
Platform: UNKNOWN
